{
  "device_id": "a5a25d38-d067-4e9d-8ed6-622de26c1a4aR",
  "user_id": null,
  "timestamp": 1576972626961,
  "event_id": 278,
  "session_id": 1576972532372,
  "event_type": "view collection",
  "version_name": null,
  "platform": "Web",
  "os_name": "Chrome",
  "os_version": "79",
  "device_model": "Mac",
  "device_manufacturer": null,
  "language": "en-US",
  "carrier": null,
  "api_properties": {},
  "event_properties": {
    "name": "teamprompts-app",
    "nodeEnv": "production",
    "version": "0.19.0",
    "collectionName": "all",
    "loadTime": "TBD",
    "promptsDisplayed": "TBD",
    "promptsInCollection": 41
  },
  "user_properties": {},
  "uuid": "a0827d06-1dee-48a2-8810-75c4b3724977",
  "library": {
    "name": "amplitude-js",
    "version": "5.7.0"
  },
  "sequence_number": 278,
  "groups": {},
  "group_properties": {},
  "user_agent": "Mozilla/5.0 (Macintosh; Intel Mac OS X 10_14_6) AppleWebKit/537.36 (KHTML, like Gecko) Chrome/79.0.3945.88 Safari/537.36"
}
